chi_sdk/__init__.py
chi_sdk/admin.py
chi_sdk/models.py
chi_sdk/renderer.py
chi_sdk/sdk.py
chi_sdk/bin/chi-tui
chi_sdk/bin/chi-tui.exe
chi_sdk/tui_runner/__init__.py
chi_sdk/tui_runner/runner.py
chi_sdk-0.0.5.dist-info/licenses/LICENSE
chi_sdk-0.0.5.dist-info/METADATA
chi_sdk-0.0.5.dist-info/WHEEL
chi_sdk-0.0.5.dist-info/entry_points.txt
chi_sdk-0.0.5.dist-info/top_level.txt
chi_sdk-0.0.5.dist-info/RECORD
