Metadata-Version: 2.4
Name: chi-sdk
Version: 0.0.5
Summary: Build beautiful Terminal UIs for Python CLIs without rewriting your code
Author-email: CHI TUI <devnull@example.com>
License: Apache-2.0 for SDK, AGPL-3.0 for TUI binary (see LICENSE files)
Project-URL: homepage, https://github.com/jacekjursza/chi_sdk
Project-URL: repository, https://github.com/jacekjursza/chi_sdk
Classifier: License :: OSI Approved :: Apache Software License
Requires-Python: >=3.11
License-File: LICENSE
Requires-Dist: click>=8
Requires-Dist: pydantic>=2
Provides-Extra: dev
Requires-Dist: pre-commit>=3.6; extra == "dev"
Requires-Dist: black>=24.3; extra == "dev"
Requires-Dist: ruff>=0.4; extra == "dev"
Requires-Dist: pytest>=7; extra == "dev"
Dynamic: license-file
